umato/__init__.py
umato/distances.py
umato/layouts.py
umato/nndescent.py
umato/rp_tree.py
umato/sparse.py
umato/sparse_nndescent.py
umato/umap_.py
umato/umato_.py
umato/utils.py
umato-1.0.0.dist-info/licenses/LICENSE
umato-1.0.0.dist-info/METADATA
umato-1.0.0.dist-info/WHEEL
umato-1.0.0.dist-info/top_level.txt
umato-1.0.0.dist-info/RECORD
