Metadata-Version: 2.4
Name: umato
Version: 1.0.0
Summary: Python Implementation of UMATO (Uniform Manifold Approximation with Two-Phase Optimization)
Author-email: Hyeon Jeon <hj@hcil.snu.ac.kr>, Kwon Ko <kwonko@stanford.edu>, Soohyun Lee <shlee@hcil.snu.ac.kr>, Jake Hyun <jakehyun@snu.ac.kr>, Taehyun Yang <0705danny@snu.ac.kr>, Gyehun Go <rotation_430@snu.ac.kr>, Jaemin Jo <jmjo@skku.edu>, Jinwook Seo <jseo@snu.ac.kr>
Maintainer-email: Hyeon Jeon <hj@hcil.snu.ac.kr>
License: MIT (includes BSD-licensed components from UMAP)
Project-URL: Homepage, https://github.com/hyungkwonko/umato
Keywords: UMATO,UMAP,T-SNE,Uniform Manifold Approximation,Two-Phase Optimization,Dimensionality Reduction,Manifold,Machine Learning,Data Science
Classifier: Programming Language :: Python :: 3
Classifier: License :: OSI Approved :: MIT License
Classifier: Operating System :: OS Independent
Requires-Python: >=3.9
License-File: LICENSE
Requires-Dist: scikit-learn
Requires-Dist: numpy
Requires-Dist: scipy
Requires-Dist: numba
Requires-Dist: joblib
Dynamic: license-file
